magic_dao/__init__.py
magic_dao/magic.py
magic_dao/setup.py
magic_dao-0.0.1.dist-info/METADATA
magic_dao-0.0.1.dist-info/WHEEL
magic_dao-0.0.1.dist-info/top_level.txt
magic_dao-0.0.1.dist-info/RECORD
