Metadata-Version: 2.1
Name: magic-dao
Version: 0.0.1
Summary: Magic commands used in NUS DAO classes
Home-page: https://github.com/XiongPengNUS/magic_dao
Author: Peng Xiong
Author-email: xiongpengnus@gmail.com
License: UNKNOWN
Platform: UNKNOWN
Classifier: Programming Language :: Python :: 3
Classifier: Operating System :: OS Independent
